fol_parser/ANTLR/.DS_Store
fol_parser/ANTLR/.antlr/FOL.interp
fol_parser/ANTLR/.antlr/FOL.tokens
fol_parser/ANTLR/.antlr/FOLBaseListener.java
fol_parser/ANTLR/.antlr/FOLLexer.interp
fol_parser/ANTLR/.antlr/FOLLexer.java
fol_parser/ANTLR/.antlr/FOLLexer.tokens
fol_parser/ANTLR/.antlr/FOLListener.java
fol_parser/ANTLR/.antlr/FOLParser.java
fol_parser/ANTLR/FOL.g4
fol_parser/ANTLR/FOL.interp
fol_parser/ANTLR/FOL.tokens
fol_parser/ANTLR/FOLLexer.interp
fol_parser/ANTLR/FOLLexer.py
fol_parser/ANTLR/FOLLexer.tokens
fol_parser/ANTLR/FOLListener.py
fol_parser/ANTLR/FOLParser.py
fol_parser/ANTLR/__init__.py
fol_parser/__init__.py
fol_parser/graphs/parse_tree.gv
fol_parser/graphs/parse_tree.gv.pdf
fol_parser/main.py
fol_parser/tools/antlr.jar
fol_parser-0.6.0.dist-info/METADATA
fol_parser-0.6.0.dist-info/WHEEL
fol_parser-0.6.0.dist-info/RECORD
