Metadata-Version: 2.1
Name: fol_parser
Version: 0.6.0
Summary: FOL Parser
Author: Emre Kuru
Author-email: emre.kuru@ozu.edu.tr
Requires-Python: >=3.12,<4.0
Classifier: Programming Language :: Python :: 3
Classifier: Programming Language :: Python :: 3.12
Requires-Dist: antlr4-python3-runtime (>=4.13.1,<5.0.0)
Requires-Dist: graphviz (>=0.20.3,<0.21.0)
